wait_for_db/__init__.py
wait_for_db/apps.py
wait_for_db/management/commands/wait_for_db.py
wait_for_db/migrations/__init__.py
wait_for_db/tests/__init__.py
wait_for_db/tests/conftest.py
wait_for_db/tests/test_wait_for_db.py
django_wait_for_db-1.0.6.dist-info/LICENSE
django_wait_for_db-1.0.6.dist-info/METADATA
django_wait_for_db-1.0.6.dist-info/WHEEL
django_wait_for_db-1.0.6.dist-info/RECORD
